{"nodes": [{"id": "users_saitejamantha_documents_new_project_multi_robot_coordinator_py", "label": "coordinator.py", "file_type": "code", "source_file": "multi_robot/coordinator.py", "source_location": "L1"}, {"id": "multi_robot_coordinator_robotstate", "label": "RobotState", "file_type": "code", "source_file": "multi_robot/coordinator.py", "source_location": "L32"}, {"id": "multi_robot_coordinator_robotcoordinator", "label": "RobotCoordinator", "file_type": "code", "source_file": "multi_robot/coordinator.py", "source_location": "L48"}, {"id": "multi_robot_coordinator_robotcoordinator_init", "label": ".__init__()", "file_type": "code", "source_file": "multi_robot/coordinator.py", "source_location": "L77"}, {"id": "ndarray", "label": "ndarray", "file_type": "code", "source_file": "multi_robot/coordinator.py", "source_location": "L77"}, {"id": "multi_robot_coordinator_robotcoordinator_compute_adaptive_h", "label": "._compute_adaptive_h()", "file_type": "code", "source_file": "multi_robot/coordinator.py", "source_location": "L106"}, {"id": "multi_robot_coordinator_robotcoordinator_step", "label": ".step()", "file_type": "code", "source_file": "multi_robot/coordinator.py", "source_location": "L125"}, {"id": "multi_robot_coordinator_rationale_1", "label": "multi_robot/coordinator.py ---------------------------- Per-robot coordination l", "file_type": "rationale", "source_file": "multi_robot/coordinator.py", "source_location": "L1"}, {"id": "multi_robot_coordinator_rationale_33", "label": "All mutable state for a single robot across timesteps.", "file_type": "rationale", "source_file": "multi_robot/coordinator.py", "source_location": "L33"}, {"id": "multi_robot_coordinator_rationale_49", "label": "Implements Algorithm 1 from MR-NAMO (Paper 5) with three novel extensions:", "file_type": "rationale", "source_file": "multi_robot/coordinator.py", "source_location": "L49"}, {"id": "multi_robot_coordinator_rationale_107", "label": "h = clamp(ceil(mean_pairwise_Manhattan / 2), 5, 20).", "file_type": "rationale", "source_file": "multi_robot/coordinator.py", "source_location": "L107"}, {"id": "multi_robot_coordinator_rationale_130", "label": "Run one timestep for ALL robots simultaneously.         Returns next_cells: {rob", "file_type": "rationale", "source_file": "multi_robot/coordinator.py", "source_location": "L130"}], "edges": [{"source": "users_saitejamantha_documents_new_project_multi_robot_coordinator_py", "target": "math", "relation": "imports", "context": "import", "confidence": "EXTRACTED", "source_file": "multi_robot/coordinator.py", "source_location": "L16", "weight": 1.0}, {"source": "users_saitejamantha_documents_new_project_multi_robot_coordinator_py", "target": "random", "relation": "imports", "context": "import", "confidence": "EXTRACTED", "source_file": "multi_robot/coordinator.py", "source_location": "L17", "weight": 1.0}, {"source": "users_saitejamantha_documents_new_project_multi_robot_coordinator_py", "target": "numpy", "relation": "imports", "context": "import", "confidence": "EXTRACTED", "source_file": "multi_robot/coordinator.py", "source_location": "L18", "weight": 1.0}, {"source": "users_saitejamantha_documents_new_project_multi_robot_coordinator_py", "target": "dataclasses", "relation": "imports_from", "context": "import", "confidence": "EXTRACTED", "source_file": "multi_robot/coordinator.py", "source_location": "L19", "weight": 1.0}, {"source": "users_saitejamantha_documents_new_project_multi_robot_coordinator_py", "target": "typing", "relation": "imports_from", "context": "import", "confidence": "EXTRACTED", "source_file": "multi_robot/coordinator.py", "source_location": "L20", "weight": 1.0}, {"source": "users_saitejamantha_documents_new_project_multi_robot_coordinator_py", "target": "core_planner", "relation": "imports_from", "context": "import", "confidence": "EXTRACTED", "source_file": "multi_robot/coordinator.py", "source_location": "L22", "weight": 1.0}, {"source": "users_saitejamantha_documents_new_project_multi_robot_coordinator_py", "target": "multi_robot_conflict_detection", "relation": "imports_from", "context": "import", "confidence": "EXTRACTED", "source_file": "multi_robot/coordinator.py", "source_location": "L23", "weight": 1.0}, {"source": "users_saitejamantha_documents_new_project_multi_robot_coordinator_py", "target": "multi_robot_deadlock_resolution", "relation": "imports_from", "context": "import", "confidence": "EXTRACTED", "source_file": "multi_robot/coordinator.py", "source_location": "L26", "weight": 1.0}, {"source": "users_saitejamantha_documents_new_project_multi_robot_coordinator_py", "target": "multi_robot_belief_broadcaster", "relation": "imports_from", "context": "import", "confidence": "EXTRACTED", "source_file": "multi_robot/coordinator.py", "source_location": "L27", "weight": 1.0}, {"source": "users_saitejamantha_documents_new_project_multi_robot_coordinator_py", "target": "social_social_costmap", "relation": "imports_from", "context": "import", "confidence": "EXTRACTED", "source_file": "multi_robot/coordinator.py", "source_location": "L28", "weight": 1.0}, {"source": "users_saitejamantha_documents_new_project_multi_robot_coordinator_py", "target": "multi_robot_coordinator_robotstate", "relation": "contains", "confidence": "EXTRACTED", "source_file": "multi_robot/coordinator.py", "source_location": "L32", "weight": 1.0}, {"source": "users_saitejamantha_documents_new_project_multi_robot_coordinator_py", "target": "multi_robot_coordinator_robotcoordinator", "relation": "contains", "confidence": "EXTRACTED", "source_file": "multi_robot/coordinator.py", "source_location": "L48", "weight": 1.0}, {"source": "multi_robot_coordinator_robotcoordinator", "target": "multi_robot_coordinator_robotcoordinator_init", "relation": "method", "confidence": "EXTRACTED", "source_file": "multi_robot/coordinator.py", "source_location": "L77", "weight": 1.0}, {"source": "multi_robot_coordinator_robotcoordinator_init", "target": "ndarray", "relation": "references", "context": "parameter_type", "confidence": "EXTRACTED", "source_file": "multi_robot/coordinator.py", "source_location": "L77", "weight": 1.0}, {"source": "multi_robot_coordinator_robotcoordinator", "target": "multi_robot_coordinator_robotcoordinator_compute_adaptive_h", "relation": "method", "confidence": "EXTRACTED", "source_file": "multi_robot/coordinator.py", "source_location": "L106", "weight": 1.0}, {"source": "multi_robot_coordinator_robotcoordinator_compute_adaptive_h", "target": "multi_robot_coordinator_robotstate", "relation": "references", "context": "generic_arg", "confidence": "EXTRACTED", "source_file": "multi_robot/coordinator.py", "source_location": "L106", "weight": 1.0}, {"source": "multi_robot_coordinator_robotcoordinator", "target": "multi_robot_coordinator_robotcoordinator_step", "relation": "method", "confidence": "EXTRACTED", "source_file": "multi_robot/coordinator.py", "source_location": "L125", "weight": 1.0}, {"source": "multi_robot_coordinator_robotcoordinator_step", "target": "multi_robot_coordinator_robotstate", "relation": "references", "context": "generic_arg", "confidence": "EXTRACTED", "source_file": "multi_robot/coordinator.py", "source_location": "L125", "weight": 1.0}, {"source": "multi_robot_coordinator_robotcoordinator_step", "target": "multi_robot_coordinator_robotcoordinator_compute_adaptive_h", "relation": "calls", "context": "call", "confidence": "EXTRACTED", "source_file": "multi_robot/coordinator.py", "source_location": "L137", "weight": 1.0}, {"source": "multi_robot_coordinator_rationale_1", "target": "users_saitejamantha_documents_new_project_multi_robot_coordinator_py", "relation": "rationale_for", "confidence": "EXTRACTED", "source_file": "multi_robot/coordinator.py", "source_location": "L1", "weight": 1.0}, {"source": "multi_robot_coordinator_rationale_33", "target": "multi_robot_coordinator_robotstate", "relation": "rationale_for", "confidence": "EXTRACTED", "source_file": "multi_robot/coordinator.py", "source_location": "L33", "weight": 1.0}, {"source": "multi_robot_coordinator_rationale_49", "target": "multi_robot_coordinator_robotcoordinator", "relation": "rationale_for", "confidence": "EXTRACTED", "source_file": "multi_robot/coordinator.py", "source_location": "L49", "weight": 1.0}, {"source": "multi_robot_coordinator_rationale_107", "target": "multi_robot_coordinator_robotcoordinator_compute_adaptive_h", "relation": "rationale_for", "confidence": "EXTRACTED", "source_file": "multi_robot/coordinator.py", "source_location": "L107", "weight": 1.0}, {"source": "multi_robot_coordinator_rationale_130", "target": "multi_robot_coordinator_robotcoordinator_step", "relation": "rationale_for", "confidence": "EXTRACTED", "source_file": "multi_robot/coordinator.py", "source_location": "L130", "weight": 1.0}], "raw_calls": [{"caller_nid": "multi_robot_coordinator_robotcoordinator_init", "callee": "ConflictDetector", "is_member_call": false, "source_file": "/Users/saitejamantha/Documents/New project/multi_robot/coordinator.py", "source_location": "L100"}, {"caller_nid": "multi_robot_coordinator_robotcoordinator_compute_adaptive_h", "callee": "values", "is_member_call": true, "source_file": "/Users/saitejamantha/Documents/New project/multi_robot/coordinator.py", "source_location": "L108"}, {"caller_nid": "multi_robot_coordinator_robotcoordinator_compute_adaptive_h", "callee": "append", "is_member_call": true, "source_file": "/Users/saitejamantha/Documents/New project/multi_robot/coordinator.py", "source_location": "L115"}, {"caller_nid": "multi_robot_coordinator_robotcoordinator_compute_adaptive_h", "callee": "ceil", "is_member_call": true, "source_file": "/Users/saitejamantha/Documents/New project/multi_robot/coordinator.py", "source_location": "L119"}, {"caller_nid": "multi_robot_coordinator_robotcoordinator_step", "callee": "values", "is_member_call": true, "source_file": "/Users/saitejamantha/Documents/New project/multi_robot/coordinator.py", "source_location": "L140"}, {"caller_nid": "multi_robot_coordinator_robotcoordinator_step", "callee": "items", "is_member_call": true, "source_file": "/Users/saitejamantha/Documents/New project/multi_robot/coordinator.py", "source_location": "L145"}, {"caller_nid": "multi_robot_coordinator_robotcoordinator_step", "callee": "values", "is_member_call": true, "source_file": "/Users/saitejamantha/Documents/New project/multi_robot/coordinator.py", "source_location": "L191"}, {"caller_nid": "multi_robot_coordinator_robotcoordinator_step", "callee": "a_star", "is_member_call": false, "source_file": "/Users/saitejamantha/Documents/New project/multi_robot/coordinator.py", "source_location": "L199"}, {"caller_nid": "multi_robot_coordinator_robotcoordinator_step", "callee": "detect", "is_member_call": true, "source_file": "/Users/saitejamantha/Documents/New project/multi_robot/coordinator.py", "source_location": "L224"}, {"caller_nid": "multi_robot_coordinator_robotcoordinator_step", "callee": "add", "is_member_call": true, "source_file": "/Users/saitejamantha/Documents/New project/multi_robot/coordinator.py", "source_location": "L247"}, {"caller_nid": "multi_robot_coordinator_robotcoordinator_step", "callee": "append", "is_member_call": true, "source_file": "/Users/saitejamantha/Documents/New project/multi_robot/coordinator.py", "source_location": "L268"}, {"caller_nid": "multi_robot_coordinator_robotcoordinator_step", "callee": "extend", "is_member_call": true, "source_file": "/Users/saitejamantha/Documents/New project/multi_robot/coordinator.py", "source_location": "L273"}, {"caller_nid": "multi_robot_coordinator_robotcoordinator_step", "callee": "resolve_sr_social", "is_member_call": true, "source_file": "/Users/saitejamantha/Documents/New project/multi_robot/coordinator.py", "source_location": "L297"}, {"caller_nid": "multi_robot_coordinator_robotcoordinator_step", "callee": "resolve_social", "is_member_call": true, "source_file": "/Users/saitejamantha/Documents/New project/multi_robot/coordinator.py", "source_location": "L302"}, {"caller_nid": "multi_robot_coordinator_robotcoordinator_step", "callee": "resolve_sr_width", "is_member_call": true, "source_file": "/Users/saitejamantha/Documents/New project/multi_robot/coordinator.py", "source_location": "L306"}, {"caller_nid": "multi_robot_coordinator_robotcoordinator_step", "callee": "resolve_repulsive", "is_member_call": true, "source_file": "/Users/saitejamantha/Documents/New project/multi_robot/coordinator.py", "source_location": "L310"}, {"caller_nid": "multi_robot_coordinator_robotcoordinator_step", "callee": "items", "is_member_call": true, "source_file": "/Users/saitejamantha/Documents/New project/multi_robot/coordinator.py", "source_location": "L314"}, {"caller_nid": "multi_robot_coordinator_robotcoordinator_step", "callee": "items", "is_member_call": true, "source_file": "/Users/saitejamantha/Documents/New project/multi_robot/coordinator.py", "source_location": "L318"}, {"caller_nid": "multi_robot_coordinator_robotcoordinator_step", "callee": "randint", "is_member_call": true, "source_file": "/Users/saitejamantha/Documents/New project/multi_robot/coordinator.py", "source_location": "L322"}, {"caller_nid": "multi_robot_coordinator_robotcoordinator_step", "callee": "add", "is_member_call": true, "source_file": "/Users/saitejamantha/Documents/New project/multi_robot/coordinator.py", "source_location": "L324"}, {"caller_nid": "multi_robot_coordinator_robotcoordinator_step", "callee": "get", "is_member_call": true, "source_file": "/Users/saitejamantha/Documents/New project/multi_robot/coordinator.py", "source_location": "L327"}, {"caller_nid": "multi_robot_coordinator_robotcoordinator_step", "callee": "a_star", "is_member_call": false, "source_file": "/Users/saitejamantha/Documents/New project/multi_robot/coordinator.py", "source_location": "L331"}, {"caller_nid": "multi_robot_coordinator_robotcoordinator_step", "callee": "values", "is_member_call": true, "source_file": "/Users/saitejamantha/Documents/New project/multi_robot/coordinator.py", "source_location": "L369"}, {"caller_nid": "multi_robot_coordinator_robotcoordinator_step", "callee": "pop", "is_member_call": true, "source_file": "/Users/saitejamantha/Documents/New project/multi_robot/coordinator.py", "source_location": "L371"}]}